LICENSE
README.md
setup.py
nowcast_lstm/LSTM.py
nowcast_lstm/__init__.py
nowcast_lstm/data_setup.py
nowcast_lstm/interval_prediction.py
nowcast_lstm/model_selection.py
nowcast_lstm/modelling.py
nowcast_lstm/mv_lstm.py
nowcast_lstm.egg-info/PKG-INFO
nowcast_lstm.egg-info/SOURCES.txt
nowcast_lstm.egg-info/dependency_links.txt
nowcast_lstm.egg-info/top_level.txt
tests/__init__.py
tests/test_LSTM.py
tests/test_data_setup.py
tests/test_modelling.py