Metadata-Version: 2.1
Name: nowcast-lstm
Version: 0.2.5
Summary: Code for running LSTM neural networks on economic data for nowcasting
Home-page: https://github.com/dhopp1/nowcast_lstm
Author: Daniel Hopp
Author-email: daniel.hopp@un.org
Classifier: Programming Language :: Python :: 3
Classifier: License :: OSI Approved :: MIT License
Classifier: Operating System :: OS Independent
Requires-Python: >=3.6
License-File: LICENSE
